reduce_mem_usage/__init__.py
reduce_mem_usage-0.1.0.dist-info/METADATA
reduce_mem_usage-0.1.0.dist-info/WHEEL
reduce_mem_usage-0.1.0.dist-info/top_level.txt
reduce_mem_usage-0.1.0.dist-info/RECORD
